{
  "workspace": [
    "./packages/core",
    "./packages/components",
    "./packages/theme-default",
    "./packages/docs",
    "./packages/inspector"
  ],
  "unstable": ["raw-imports"],
  "compilerOptions": {
    "lib": [
      "deno.ns",
      "DOM",
      "DOM.Iterable",
      "DOM.AsyncIterable",
      "ESNext"
    ]
  },
  "nodeModulesDir": "auto",
  "tasks": {
    "dev": "deno run --allow-all packages/docs/serve.ts",
    "build:docs": "deno run --allow-all packages/docs/serve.ts --build",
    "build": "deno run --allow-all scripts/build.ts",
    "build:cdn": "deno run --allow-all scripts/build-cdn.ts",
    "build:all": "deno run --allow-all scripts/build.ts && deno run --allow-all scripts/build-cdn.ts",
    "version": "deno run --allow-all scripts/version.ts",
    "publish": "deno run --allow-all scripts/publish.ts",
    "publish:live": "deno run --allow-all scripts/publish.ts --publish"
  }
}
